MANIFEST.in
README.rst
setup.cfg
setup.py
docs/HISTORY.rst
docs/INSTALL.rst
docs/LICENSE.GPL
docs/LICENSE.rst
redomino/__init__.py
redomino.odttransforms.egg-info/PKG-INFO
redomino.odttransforms.egg-info/SOURCES.txt
redomino.odttransforms.egg-info/dependency_links.txt
redomino.odttransforms.egg-info/entry_points.txt
redomino.odttransforms.egg-info/namespace_packages.txt
redomino.odttransforms.egg-info/not-zip-safe
redomino.odttransforms.egg-info/requires.txt
redomino.odttransforms.egg-info/top_level.txt
redomino/odttransforms/__init__.py
redomino/odttransforms/configure.zcml
redomino/odttransforms/mimetype.py
redomino/odttransforms/setuphandlers.py
redomino/odttransforms/testing.py
redomino/odttransforms/Extensions/Install.py
redomino/odttransforms/profiles/default/metadata.xml
redomino/odttransforms/profiles/default/redomino.odttransforms.txt
redomino/odttransforms/profiles/uninstall/redomino.odttransforms_uninstall.txt
redomino/odttransforms/tests/__init__.py
redomino/odttransforms/tests/input.odt
redomino/odttransforms/tests/test_odt_transform.py
redomino/odttransforms/tests/test_portal.py
redomino/odttransforms/tests/test_uninstall.py
redomino/odttransforms/transforms/__init__.py
redomino/odttransforms/transforms/odt_transforms.py